linesep/__init__.py
linesep/funcs.py
linesep/py.typed
linesep/splitters.py
linesep-0.5.1.dist-info/METADATA
linesep-0.5.1.dist-info/WHEEL
linesep-0.5.1.dist-info/licenses/LICENSE
linesep-0.5.1.dist-info/RECORD
