Metadata-Version: 2.3
Name: linesep
Version: 0.5.1
Summary: Handling lines with arbitrary separators
Project-URL: Source Code, https://github.com/jwodder/linesep
Project-URL: Bug Tracker, https://github.com/jwodder/linesep/issues
Project-URL: Documentation, https://linesep.readthedocs.io
Author-email: John Thorvald Wodder II <linesep@varonathe.org>
License: MIT
Keywords: delimiters,line break,line-ending,linebreak,newline,paragraphs,separator
Classifier: Intended Audience :: Developers
Classifier: License :: OSI Approved :: MIT License
Classifier: Operating System :: OS Independent
Classifier: Programming Language :: Python :: 3
Classifier: Programming Language :: Python :: 3 :: Only
Classifier: Programming Language :: Python :: 3.8
Classifier: Programming Language :: Python :: 3.9
Classifier: Programming Language :: Python :: 3.10
Classifier: Programming Language :: Python :: 3.11
Classifier: Programming Language :: Python :: 3.12
Classifier: Programming Language :: Python :: 3.13
Classifier: Programming Language :: Python :: Implementation :: CPython
Classifier: Programming Language :: Python :: Implementation :: PyPy
Classifier: Topic :: Text Processing
Classifier: Topic :: Utilities
Classifier: Typing :: Typed
Requires-Python: >=3.8
